[
  {
    "average_reward": 0.047598487100356024,
    "average_turns": 7.0,
    "envs": 31,
    "episodes": 123,
    "invalid_move_rate": 0.6910569105691057,
    "method": "fixed_prompt",
    "repeated_action_rate": 0.6991869918699187,
    "slice": "support_group",
    "success_rate": 0.1951219512195122,
    "value": "generic_fallback"
  },
  {
    "average_reward": 0.17285855924735086,
    "average_turns": 13.291666666666666,
    "envs": 19,
    "episodes": 72,
    "invalid_move_rate": 0.2222222222222222,
    "method": "fixed_prompt",
    "repeated_action_rate": 0.8333333333333334,
    "slice": "support_group",
    "success_rate": 0.16666666666666666,
    "value": "supported_policy_family"
  },
  {
    "average_reward": 0.0,
    "average_turns": 7.8,
    "envs": 10,
    "episodes": 60,
    "invalid_move_rate": 0.3,
    "method": "fixed_prompt",
    "repeated_action_rate": 0.7,
    "slice": "category",
    "success_rate": 0.45,
    "value": "board_game"
  },
  {
    "average_reward": 0.0,
    "average_turns": 3.8333333333333335,
    "envs": 2,
    "episodes": 12,
    "invalid_move_rate": 0.5,
    "method": "fixed_prompt",
    "repeated_action_rate": 1.0,
    "slice": "category",
    "success_rate": 0.5,
    "value": "card_game"
  },
  {
    "average_reward": 0.5917136591478697,
    "average_turns": 8.0,
    "envs": 4,
    "episodes": 12,
    "invalid_move_rate": 0.5,
    "method": "fixed_prompt",
    "repeated_action_rate": 0.5,
    "slice": "category",
    "success_rate": 0.0,
    "value": "deduction"
  },
  {
    "average_reward": 0.24030660697327363,
    "average_turns": 6.166666666666667,
    "envs": 6,
    "episodes": 18,
    "invalid_move_rate": 0.8888888888888888,
    "method": "fixed_prompt",
    "repeated_action_rate": 0.7222222222222222,
    "slice": "category",
    "success_rate": 0.0,
    "value": "language_puzzle"
  },
  {
    "average_reward": 0.19444444444444445,
    "average_turns": 10.0,
    "envs": 6,
    "episodes": 18,
    "invalid_move_rate": 0.5555555555555556,
    "method": "fixed_prompt",
    "repeated_action_rate": 0.8888888888888888,
    "slice": "category",
    "success_rate": 0.0,
    "value": "planning"
  },
  {
    "average_reward": 0.011761352825422391,
    "average_turns": 7.518518518518518,
    "envs": 9,
    "episodes": 27,
    "invalid_move_rate": 0.8888888888888888,
    "method": "fixed_prompt",
    "repeated_action_rate": 0.8888888888888888,
    "slice": "category",
    "success_rate": 0.0,
    "value": "puzzle"
  },
  {
    "average_reward": 0.0,
    "average_turns": 24.666666666666668,
    "envs": 3,
    "episodes": 18,
    "invalid_move_rate": 0.16666666666666666,
    "method": "fixed_prompt",
    "repeated_action_rate": 1.0,
    "slice": "category",
    "success_rate": 0.16666666666666666,
    "value": "social_game"
  },
  {
    "average_reward": 0.16982171208740487,
    "average_turns": 13.666666666666666,
    "envs": 6,
    "episodes": 18,
    "invalid_move_rate": 0.3333333333333333,
    "method": "fixed_prompt",
    "repeated_action_rate": 0.6666666666666666,
    "slice": "category",
    "success_rate": 0.0,
    "value": "stochastic_decision"
  },
  {
    "average_reward": 0.0,
    "average_turns": 2.0,
    "envs": 4,
    "episodes": 12,
    "invalid_move_rate": 1.0,
    "method": "fixed_prompt",
    "repeated_action_rate": 0.25,
    "slice": "category",
    "success_rate": 0.0,
    "value": "symbolic_puzzle"
  },
  {
    "average_reward": 0.047598487100356024,
    "average_turns": 7.0,
    "envs": 31,
    "episodes": 123,
    "invalid_move_rate": 0.6910569105691057,
    "method": "textgrad_policy_iteration",
    "repeated_action_rate": 0.6991869918699187,
    "slice": "support_group",
    "success_rate": 0.1951219512195122,
    "value": "generic_fallback"
  },
  {
    "average_reward": 0.6257887613551846,
    "average_turns": 11.069444444444445,
    "envs": 19,
    "episodes": 72,
    "invalid_move_rate": 0.041666666666666664,
    "method": "textgrad_policy_iteration",
    "repeated_action_rate": 0.75,
    "slice": "support_group",
    "success_rate": 0.6666666666666666,
    "value": "supported_policy_family"
  },
  {
    "average_reward": 0.2,
    "average_turns": 7.2,
    "envs": 10,
    "episodes": 60,
    "invalid_move_rate": 0.3,
    "method": "textgrad_policy_iteration",
    "repeated_action_rate": 0.7,
    "slice": "category",
    "success_rate": 0.55,
    "value": "board_game"
  },
  {
    "average_reward": 0.0,
    "average_turns": 3.8333333333333335,
    "envs": 2,
    "episodes": 12,
    "invalid_move_rate": 0.5,
    "method": "textgrad_policy_iteration",
    "repeated_action_rate": 1.0,
    "slice": "category",
    "success_rate": 0.5,
    "value": "card_game"
  },
  {
    "average_reward": 1.0,
    "average_turns": 4.333333333333333,
    "envs": 4,
    "episodes": 12,
    "invalid_move_rate": 0.0,
    "method": "textgrad_policy_iteration",
    "repeated_action_rate": 0.25,
    "slice": "category",
    "success_rate": 1.0,
    "value": "deduction"
  },
  {
    "average_reward": 0.24030660697327363,
    "average_turns": 6.166666666666667,
    "envs": 6,
    "episodes": 18,
    "invalid_move_rate": 0.8888888888888888,
    "method": "textgrad_policy_iteration",
    "repeated_action_rate": 0.7222222222222222,
    "slice": "category",
    "success_rate": 0.0,
    "value": "language_puzzle"
  },
  {
    "average_reward": 0.875,
    "average_turns": 7.5,
    "envs": 6,
    "episodes": 18,
    "invalid_move_rate": 0.16666666666666666,
    "method": "textgrad_policy_iteration",
    "repeated_action_rate": 0.8888888888888888,
    "slice": "category",
    "success_rate": 0.8333333333333334,
    "value": "planning"
  },
  {
    "average_reward": 0.1399664810305506,
    "average_turns": 6.222222222222222,
    "envs": 9,
    "episodes": 27,
    "invalid_move_rate": 0.8888888888888888,
    "method": "textgrad_policy_iteration",
    "repeated_action_rate": 0.7777777777777778,
    "slice": "category",
    "success_rate": 0.1111111111111111,
    "value": "puzzle"
  },
  {
    "average_reward": 0.0,
    "average_turns": 24.666666666666668,
    "envs": 3,
    "episodes": 18,
    "invalid_move_rate": 0.16666666666666666,
    "method": "textgrad_policy_iteration",
    "repeated_action_rate": 1.0,
    "slice": "category",
    "success_rate": 0.16666666666666666,
    "value": "social_game"
  },
  {
    "average_reward": 0.16982171208740487,
    "average_turns": 13.666666666666666,
    "envs": 6,
    "episodes": 18,
    "invalid_move_rate": 0.3333333333333333,
    "method": "textgrad_policy_iteration",
    "repeated_action_rate": 0.6666666666666666,
    "slice": "category",
    "success_rate": 0.0,
    "value": "stochastic_decision"
  },
  {
    "average_reward": 0.0,
    "average_turns": 2.0,
    "envs": 4,
    "episodes": 12,
    "invalid_move_rate": 1.0,
    "method": "textgrad_policy_iteration",
    "repeated_action_rate": 0.25,
    "slice": "category",
    "success_rate": 0.0,
    "value": "symbolic_puzzle"
  }
]
